imapdump/__init__.py
imapdump/__main__.py
imapdump/dump.py
imapdump/config/__init__.py
imapdump/config/default_values.py
imapdump/config/fileconfig.py
imapdump/config/imapdump_config.py
imapdump/db/__init__.py
imapdump/db/data_service.py
imapdump/enums/__init__.py
imapdump/enums/imap_encryption_mode.py
imapdump/imap/__init__.py
imapdump/imap/dumper.py
imapdump/models/__init__.py
imapdump/models/base.py
imapdump/models/mail.py
imapdump/utils/__init__.py
imapdump/utils/hash_utils.py
imapdump/utils/str_utils.py
imapdump-0.7.3.dist-info/METADATA
imapdump-0.7.3.dist-info/WHEEL
imapdump-0.7.3.dist-info/entry_points.txt
imapdump-0.7.3.dist-info/top_level.txt
imapdump-0.7.3.dist-info/RECORD
