Metadata-Version: 2.4
Name: imapdump
Version: 0.7.3
Summary: A cli utility for dumping emails as EML files to a folder.
Author-email: das-kaesebrot <49565683+das-kaesebrot@users.noreply.github.com>
Project-URL: Homepage, https://github.com/das-kaesebrot/imapdump
Project-URL: Bug Tracker, https://github.com/das-kaesebrot/imapdump/issues
Classifier: Programming Language :: Python :: 3
Classifier: Operating System :: OS Independent
Classifier: Development Status :: 4 - Beta
Classifier: Intended Audience :: System Administrators
Classifier: License :: OSI Approved :: GNU Affero General Public License v3 or later (AGPLv3+)
Classifier: Environment :: Console
Requires-Python: >=3.9
Requires-Dist: dacite==1.9.2; python_version >= "3.6"
Requires-Dist: greenlet==3.3.0; python_version >= "3.9"
Requires-Dist: imapclient==3.0.1; python_full_version >= "3.7.0"
Requires-Dist: pyyaml==6.0.3; python_version >= "3.8"
Requires-Dist: sqlalchemy==2.0.45; python_version >= "3.7"
Requires-Dist: typing-extensions==4.15.0; python_version >= "3.9"
Requires-Dist: yamlargparse==1.31.1; python_version >= "3.5"
